odoo/addons/web_widget_open_tab/README.rst
odoo/addons/web_widget_open_tab/__init__.py
odoo/addons/web_widget_open_tab/__manifest__.py
odoo/addons/web_widget_open_tab/demo/res_users_view.xml
odoo/addons/web_widget_open_tab/i18n/web_widget_open_tab.pot
odoo/addons/web_widget_open_tab/readme/CONTRIBUTORS.rst
odoo/addons/web_widget_open_tab/readme/DESCRIPTION.rst
odoo/addons/web_widget_open_tab/readme/USAGE.rst
odoo/addons/web_widget_open_tab/static/description/icon.png
odoo/addons/web_widget_open_tab/static/description/index.html
odoo/addons/web_widget_open_tab/static/src/js/widget.js
odoo/addons/web_widget_open_tab/templates/assets.xml
odoo11_addon_web_widget_open_tab-11.0.1.0.0.99.dev6.dist-info/METADATA
odoo11_addon_web_widget_open_tab-11.0.1.0.0.99.dev6.dist-info/WHEEL
odoo11_addon_web_widget_open_tab-11.0.1.0.0.99.dev6.dist-info/top_level.txt
odoo11_addon_web_widget_open_tab-11.0.1.0.0.99.dev6.dist-info/RECORD
